repo_autoindex/__init__.py
repo_autoindex/_impl/__init__.py
repo_autoindex/_impl/api.py
repo_autoindex/_impl/base.py
repo_autoindex/_impl/cmd.py
repo_autoindex/_impl/kickstart.py
repo_autoindex/_impl/pulp.py
repo_autoindex/_impl/template.py
repo_autoindex/_impl/templates/index.html.j2
repo_autoindex/_impl/tree.py
repo_autoindex/_impl/yum.py
repo_autoindex/py.typed
repo_autoindex-1.2.1.dist-info/LICENSE
repo_autoindex-1.2.1.dist-info/METADATA
repo_autoindex-1.2.1.dist-info/WHEEL
repo_autoindex-1.2.1.dist-info/entry_points.txt
repo_autoindex-1.2.1.dist-info/RECORD
