Metadata-Version: 2.1
Name: repo-autoindex
Version: 1.2.1
Summary: Generic static HTML indexes of various repository types
Home-page: https://github.com/release-engineering/repo-autoindex
License: GPL-3.0-or-later
Author: Rohan McGovern
Author-email: rmcgover@redhat.com
Requires-Python: >=3.9,<4
Classifier: License :: OSI Approved :: GNU General Public License v3 or later (GPLv3+)
Classifier: Programming Language :: Python :: 3
Classifier: Programming Language :: Python :: 3.9
Classifier: Programming Language :: Python :: 3.10
Classifier: Programming Language :: Python :: 3.11
Classifier: Programming Language :: Python :: 3.12
Requires-Dist: Jinja2 (>=3.1.2)
Requires-Dist: aiohttp (>=3.8.1)
Requires-Dist: defusedxml (>=0.7.1)
Project-URL: Repository, https://github.com/release-engineering/repo-autoindex
